.VERSION
AUTHORS.rst
CONTRIBUTING.rst
HISTORY.rst
LICENSE
MANIFEST.in
Pipfile
Pipfile.lock
README.rst
USAGE.rst
dev-requirements.txt
requirements.txt
setup.cfg
setup.py
abnamrolib/.VERSION
abnamrolib/AUTHORS.rst
abnamrolib/CONTRIBUTING.rst
abnamrolib/HISTORY.rst
abnamrolib/LICENSE
abnamrolib/Pipfile
abnamrolib/Pipfile.lock
abnamrolib/README.rst
abnamrolib/USAGE.rst
abnamrolib/__init__.py
abnamrolib/_version.py
abnamrolib/abnamroics.py
abnamrolib/abnamrolib.py
abnamrolib/abnamrolibexceptions.py
abnamrolib/common.py
abnamrolib/dev-requirements.txt
abnamrolib/requirements.txt
abnamrolib.egg-info/PKG-INFO
abnamrolib.egg-info/SOURCES.txt
abnamrolib.egg-info/dependency_links.txt
abnamrolib.egg-info/not-zip-safe
abnamrolib.egg-info/requires.txt
abnamrolib.egg-info/top_level.txt
abnamrolib/__pycache__/__init__.cpython-37.pyc
abnamrolib/__pycache__/_version.cpython-37.pyc
abnamrolib/__pycache__/abnamroics.cpython-37.pyc
abnamrolib/__pycache__/abnamrolib.cpython-37.pyc
abnamrolib/__pycache__/abnamrolibexceptions.cpython-37.pyc
abnamrolib/__pycache__/common.cpython-37.pyc
docs/Makefile
docs/authors.rst
docs/conf.py
docs/contributing.rst
docs/history.rst
docs/index.rst
docs/installation.rst
docs/readme.rst
docs/usage.rst