Metadata-Version: 1.1
Name: abnamrolib
Version: 5.3.0
Summary: A library implementing authenticating to an Abn Amro account or ICS credit card and retrieving the transactions
Home-page: https://github.com/costastf/abnamrolib
Author: Costas Tyfoxylos
Author-email: costas.tyf@gmail.com
License: MIT
Keywords: abnamrolib abn amro transactions ics
Platform: UNKNOWN
Classifier: Development Status :: 4 - Beta
Classifier: Intended Audience :: Developers
Classifier: License :: OSI Approved :: MIT License
Classifier: Natural Language :: English
Classifier: Programming Language :: Python :: 3.7
